{
  "code": "0",
  "data": [
    {
      "instrument_id": "ZEUSUSDT",
      "exchange_name": "Bybit",
      "symbol": "ZEUS/USDT",
      "current_price": 0.1497,
      "index_price": 0.1502,
      "price_change_percent_24h": 0.54,
      "volume_usd": 2863127.8609,
      "volume_usd_change_percent_24h": 56.17,
      "long_volume_usd": 1395047.8827,
      "short_volume_usd": 1468079.9682,
      "long_volume_quantity": 18376,
      "short_volume_quantity": 15180,
      "open_interest_quantity": 18457898,
      "open_interest_usd": 2764993.12,
      "open_interest_change_percent_24h": -5.79,
      "long_liquidation_usd_24h": 341.46,
      "short_liquidation_usd_24h": 477.33,
      "funding_rate": 0.01,
      "next_funding_time": 1756828800000,
      "open_interest_volume_radio": 0.9657,
      "oi_vol_ratio_change_percent_24h": -39.68
    },
    {
      "instrument_id": "ZEUS_USDT",
      "exchange_name": "MEXC",
      "symbol": "ZEUS/USDT",
      "current_price": 0.1497,
      "index_price": 0.1503,
      "price_change_percent_24h": 0.6,
      "volume_usd": 963843.829,
      "volume_usd_change_percent_24h": -13.11,
      "long_volume_usd": 407451.451,
      "short_volume_usd": 556392.378,
      "long_volume_quantity": 4758,
      "short_volume_quantity": 4684,
      "open_interest_quantity": 5933680,
      "open_interest_usd": 890052,
      "open_interest_change_percent_24h": -3.82,
      "funding_rate": 0.01,
      "open_interest_volume_radio": 0.9234,
      "oi_vol_ratio_change_percent_24h": 10.68
    },
    {
      "instrument_id": "ZEUS_USDT",
      "exchange_name": "Gate",
      "symbol": "ZEUS/USDT",
      "current_price": 0.1499,
      "index_price": 0.1502,
      "price_change_percent_24h": 0.6,
      "volume_usd": 787967.449,
      "volume_usd_change_percent_24h": 4.47,
      "long_volume_usd": 390312.6,
      "short_volume_usd": 397654.849,
      "long_volume_quantity": 3220,
      "short_volume_quantity": 2943,
      "open_interest_quantity": 2680100,
      "open_interest_usd": 401746.99,
      "open_interest_change_percent_24h": -4.84,
      "long_liquidation_usd_24h": 101.92,
      "short_liquidation_usd_24h": 0,
      "funding_rate": -0.138,
      "open_interest_volume_radio": 0.5099,
      "oi_vol_ratio_change_percent_24h": -8.9
    },
    {
      "instrument_id": "PF_ZEUSUSD",
      "exchange_name": "Kraken",
      "symbol": "ZEUS/USDT",
      "current_price": 0.14918,
      "index_price": 0.150628,
      "price_change_percent_24h": 0.61,
      "volume_usd": 6623.52,
      "volume_usd_change_percent_24h": 1307.03,
      "long_volume_usd": 1535.75,
      "short_volume_usd": 5087.76,
      "long_volume_quantity": 48,
      "short_volume_quantity": 20,
      "open_interest_quantity": 248545,
      "open_interest_usd": 37077.9431,
      "open_interest_change_percent_24h": -11.14,
      "funding_rate": -0.0164638196236559,
      "next_funding_time": 1756818000000,
      "open_interest_volume_radio": 5.5979,
      "oi_vol_ratio_change_percent_24h": -93.68
    }
  ]
}