[
  {
    "bids_usd": 76879.1709,
    "bids_quantity": 1380990,
    "asks_usd": 76692.0277,
    "asks_quantity": 1349970,
    "time": 1752192000000,
    "pair_info": {
      "instrument_id": "TANSSIUSDT",
      "base_asset": "TANSSI",
      "quote_asset": "USDT",
      "exchange": "Bybit"
    },
    "fetched_at": "2025-09-05T11:34:49.756Z"
  },
  {
    "bids_usd": 83496.339,
    "bids_quantity": 1374850,
    "asks_usd": 77250.5309,
    "asks_quantity": 1244670,
    "time": 1752278400000,
    "pair_info": {
      "instrument_id": "TANSSIUSDT",
      "base_asset": "TANSSI",
      "quote_asset": "USDT",
      "exchange": "Bybit"
    },
    "fetched_at": "2025-09-05T11:34:49.756Z"
  },
  {
    "bids_usd": 32058.5415,
    "bids_quantity": 600050,
    "asks_usd": 40129.8904,
    "asks_quantity": 736040,
    "time": 1752364800000,
    "pair_info": {
      "instrument_id": "TANSSIUSDT",
      "base_asset": "TANSSI",
      "quote_asset": "USDT",
      "exchange": "Bybit"
    },
    "fetched_at": "2025-09-05T11:34:49.756Z"
  },
  {
    "bids_usd": 62480.2657,
    "bids_quantity": 1086860,
    "asks_usd": 39111.204,
    "asks_quantity": 665610,
    "time": 1752451200000,
    "pair_info": {
      "instrument_id": "TANSSIUSDT",
      "base_asset": "TANSSI",
      "quote_asset": "USDT",
      "exchange": "Bybit"
    },
    "fetched_at": "2025-09-05T11:34:49.756Z"
  },
  {
    "bids_usd": 44809.7066,
    "bids_quantity": 841370,
    "asks_usd": 41466.5895,
    "asks_quantity": 764610,
    "time": 1752537600000,
    "pair_info": {
      "instrument_id": "TANSSIUSDT",
      "base_asset": "TANSSI",
      "quote_asset": "USDT",
      "exchange": "Bybit"
    },
    "fetched_at": "2025-09-05T11:34:49.756Z"
  },
  {
    "bids_usd": 46732.4424,
    "bids_quantity": 832670,
    "asks_usd": 42227.379,
    "asks_quantity": 740480,
    "time": 1752624000000,
    "pair_info": {
      "instrument_id": "TANSSIUSDT",
      "base_asset": "TANSSI",
      "quote_asset": "USDT",
      "exchange": "Bybit"
    },
    "fetched_at": "2025-09-05T11:34:49.756Z"
  },
  {
    "bids_usd": 56336.6401,
    "bids_quantity": 858840,
    "asks_usd": 59494.7152,
    "asks_quantity": 889850,
    "time": 1752710400000,
    "pair_info": {
      "instrument_id": "TANSSIUSDT",
      "base_asset": "TANSSI",
      "quote_asset": "USDT",
      "exchange": "Bybit"
    },
    "fetched_at": "2025-09-05T11:34:49.756Z"
  },
  {
    "bids_usd": 33823.5948,
    "bids_quantity": 558680,
    "asks_usd": 36235.4177,
    "asks_quantity": 590320,
    "time": 1752796800000,
    "pair_info": {
      "instrument_id": "TANSSIUSDT",
      "base_asset": "TANSSI",
      "quote_asset": "USDT",
      "exchange": "Bybit"
    },
    "fetched_at": "2025-09-05T11:34:49.756Z"
  },
  {
    "bids_usd": 44392.0614,
    "bids_quantity": 645310,
    "asks_usd": 52771.9362,
    "asks_quantity": 752490,
    "time": 1752883200000,
    "pair_info": {
      "instrument_id": "TANSSIUSDT",
      "base_asset": "TANSSI",
      "quote_asset": "USDT",
      "exchange": "Bybit"
    },
    "fetched_at": "2025-09-05T11:34:49.756Z"
  },
  {
    "bids_usd": 47395.3119,
    "bids_quantity": 748140,
    "asks_usd": 49923.8879,
    "asks_quantity": 777080,
    "time": 1752969600000,
    "pair_info": {
      "instrument_id": "TANSSIUSDT",
      "base_asset": "TANSSI",
      "quote_asset": "USDT",
      "exchange": "Bybit"
    },
    "fetched_at": "2025-09-05T11:34:49.756Z"
  },
  {
    "bids_usd": 55747.2443,
    "bids_quantity": 902850,
    "asks_usd": 58578.7224,
    "asks_quantity": 932660,
    "time": 1753056000000,
    "pair_info": {
      "instrument_id": "TANSSIUSDT",
      "base_asset": "TANSSI",
      "quote_asset": "USDT",
      "exchange": "Bybit"
    },
    "fetched_at": "2025-09-05T11:34:49.756Z"
  },
  {
    "bids_usd": 45739.2094,
    "bids_quantity": 709450,
    "asks_usd": 52190.3372,
    "asks_quantity": 797740,
    "time": 1753142400000,
    "pair_info": {
      "instrument_id": "TANSSIUSDT",
      "base_asset": "TANSSI",
      "quote_asset": "USDT",
      "exchange": "Bybit"
    },
    "fetched_at": "2025-09-05T11:34:49.756Z"
  },
  {
    "bids_usd": 68047.0172,
    "bids_quantity": 1035470,
    "asks_usd": 43226.0268,
    "asks_quantity": 646300,
    "time": 1753228800000,
    "pair_info": {
      "instrument_id": "TANSSIUSDT",
      "base_asset": "TANSSI",
      "quote_asset": "USDT",
      "exchange": "Bybit"
    },
    "fetched_at": "2025-09-05T11:34:49.756Z"
  },
  {
    "bids_usd": 52129.9197,
    "bids_quantity": 847960,
    "asks_usd": 62499.5032,
    "asks_quantity": 995940,
    "time": 1753315200000,
    "pair_info": {
      "instrument_id": "TANSSIUSDT",
      "base_asset": "TANSSI",
      "quote_asset": "USDT",
      "exchange": "Bybit"
    },
    "fetched_at": "2025-09-05T11:34:49.756Z"
  },
  {
    "bids_usd": 68747.8238,
    "bids_quantity": 1125980,
    "asks_usd": 48688.511,
    "asks_quantity": 782720,
    "time": 1753401600000,
    "pair_info": {
      "instrument_id": "TANSSIUSDT",
      "base_asset": "TANSSI",
      "quote_asset": "USDT",
      "exchange": "Bybit"
    },
    "fetched_at": "2025-09-05T11:34:49.756Z"
  },
  {
    "bids_usd": 69448.5874,
    "bids_quantity": 1227000,
    "asks_usd": 42187.0637,
    "asks_quantity": 731010,
    "time": 1753488000000,
    "pair_info": {
      "instrument_id": "TANSSIUSDT",
      "base_asset": "TANSSI",
      "quote_asset": "USDT",
      "exchange": "Bybit"
    },
    "fetched_at": "2025-09-05T11:34:49.756Z"
  },
  {
    "bids_usd": 46884.1671,
    "bids_quantity": 858950,
    "asks_usd": 44765.9099,
    "asks_quantity": 806560,
    "time": 1753574400000,
    "pair_info": {
      "instrument_id": "TANSSIUSDT",
      "base_asset": "TANSSI",
      "quote_asset": "USDT",
      "exchange": "Bybit"
    },
    "fetched_at": "2025-09-05T11:34:49.756Z"
  },
  {
    "bids_usd": 32105.6851,
    "bids_quantity": 589050,
    "asks_usd": 48153.8307,
    "asks_quantity": 864060,
    "time": 1753660800000,
    "pair_info": {
      "instrument_id": "TANSSIUSDT",
      "base_asset": "TANSSI",
      "quote_asset": "USDT",
      "exchange": "Bybit"
    },
    "fetched_at": "2025-09-05T11:34:49.756Z"
  },
  {
    "bids_usd": 28421.8807,
    "bids_quantity": 549690,
    "asks_usd": 30043.5594,
    "asks_quantity": 570010,
    "time": 1753747200000,
    "pair_info": {
      "instrument_id": "TANSSIUSDT",
      "base_asset": "TANSSI",
      "quote_asset": "USDT",
      "exchange": "Bybit"
    },
    "fetched_at": "2025-09-05T11:34:49.756Z"
  },
  {
    "bids_usd": 30080.7391,
    "bids_quantity": 568070,
    "asks_usd": 23883.3436,
    "asks_quantity": 442200,
    "time": 1753833600000,
    "pair_info": {
      "instrument_id": "TANSSIUSDT",
      "base_asset": "TANSSI",
      "quote_asset": "USDT",
      "exchange": "Bybit"
    },
    "fetched_at": "2025-09-05T11:34:49.756Z"
  },
  {
    "bids_usd": 23433.0491,
    "bids_quantity": 426090,
    "asks_usd": 21038.5117,
    "asks_quantity": 376370,
    "time": 1753920000000,
    "pair_info": {
      "instrument_id": "TANSSIUSDT",
      "base_asset": "TANSSI",
      "quote_asset": "USDT",
      "exchange": "Bybit"
    },
    "fetched_at": "2025-09-05T11:34:49.756Z"
  },
  {
    "bids_usd": 34535.6585,
    "bids_quantity": 660660,
    "asks_usd": 21606.3018,
    "asks_quantity": 405050,
    "time": 1754006400000,
    "pair_info": {
      "instrument_id": "TANSSIUSDT",
      "base_asset": "TANSSI",
      "quote_asset": "USDT",
      "exchange": "Bybit"
    },
    "fetched_at": "2025-09-05T11:34:49.756Z"
  },
  {
    "bids_usd": 28493.3494,
    "bids_quantity": 565340,
    "asks_usd": 23631.6729,
    "asks_quantity": 460460,
    "time": 1754092800000,
    "pair_info": {
      "instrument_id": "TANSSIUSDT",
      "base_asset": "TANSSI",
      "quote_asset": "USDT",
      "exchange": "Bybit"
    },
    "fetched_at": "2025-09-05T11:34:49.756Z"
  },
  {
    "bids_usd": 20906.569,
    "bids_quantity": 417130,
    "asks_usd": 26731.9316,
    "asks_quantity": 522580,
    "time": 1754179200000,
    "pair_info": {
      "instrument_id": "TANSSIUSDT",
      "base_asset": "TANSSI",
      "quote_asset": "USDT",
      "exchange": "Bybit"
    },
    "fetched_at": "2025-09-05T11:34:49.756Z"
  },
  {
    "bids_usd": 22521.3226,
    "bids_quantity": 430170,
    "asks_usd": 29014.5838,
    "asks_quantity": 543380,
    "time": 1754265600000,
    "pair_info": {
      "instrument_id": "TANSSIUSDT",
      "base_asset": "TANSSI",
      "quote_asset": "USDT",
      "exchange": "Bybit"
    },
    "fetched_at": "2025-09-05T11:34:49.756Z"
  },
  {
    "bids_usd": 40449.2137,
    "bids_quantity": 679410,
    "asks_usd": 30871.8263,
    "asks_quantity": 509070,
    "time": 1754352000000,
    "pair_info": {
      "instrument_id": "TANSSIUSDT",
      "base_asset": "TANSSI",
      "quote_asset": "USDT",
      "exchange": "Bybit"
    },
    "fetched_at": "2025-09-05T11:34:49.756Z"
  },
  {
    "bids_usd": 36677.2252,
    "bids_quantity": 545230,
    "asks_usd": 52504.9248,
    "asks_quantity": 763740,
    "time": 1754438400000,
    "pair_info": {
      "instrument_id": "TANSSIUSDT",
      "base_asset": "TANSSI",
      "quote_asset": "USDT",
      "exchange": "Bybit"
    },
    "fetched_at": "2025-09-05T11:34:49.756Z"
  },
  {
    "bids_usd": 35527.9835,
    "bids_quantity": 632610,
    "asks_usd": 67711.1356,
    "asks_quantity": 1182690,
    "time": 1754524800000,
    "pair_info": {
      "instrument_id": "TANSSIUSDT",
      "base_asset": "TANSSI",
      "quote_asset": "USDT",
      "exchange": "Bybit"
    },
    "fetched_at": "2025-09-05T11:34:49.756Z"
  },
  {
    "bids_usd": 32724.5993,
    "bids_quantity": 588870,
    "asks_usd": 42585.4789,
    "asks_quantity": 749600,
    "time": 1754611200000,
    "pair_info": {
      "instrument_id": "TANSSIUSDT",
      "base_asset": "TANSSI",
      "quote_asset": "USDT",
      "exchange": "Bybit"
    },
    "fetched_at": "2025-09-05T11:34:49.756Z"
  },
  {
    "bids_usd": 71325.7842,
    "bids_quantity": 1023840,
    "asks_usd": 45356.4616,
    "asks_quantity": 639260,
    "time": 1754697600000,
    "pair_info": {
      "instrument_id": "TANSSIUSDT",
      "base_asset": "TANSSI",
      "quote_asset": "USDT",
      "exchange": "Bybit"
    },
    "fetched_at": "2025-09-05T11:34:49.756Z"
  },
  {
    "bids_usd": 22562.836,
    "bids_quantity": 317630,
    "asks_usd": 22632.3206,
    "asks_quantity": 313120,
    "time": 1754784000000,
    "pair_info": {
      "instrument_id": "TANSSIUSDT",
      "base_asset": "TANSSI",
      "quote_asset": "USDT",
      "exchange": "Bybit"
    },
    "fetched_at": "2025-09-05T11:34:49.756Z"
  },
  {
    "bids_usd": 30608.7146,
    "bids_quantity": 459700,
    "asks_usd": 26310.4387,
    "asks_quantity": 387100,
    "time": 1754870400000,
    "pair_info": {
      "instrument_id": "TANSSIUSDT",
      "base_asset": "TANSSI",
      "quote_asset": "USDT",
      "exchange": "Bybit"
    },
    "fetched_at": "2025-09-05T11:34:49.756Z"
  },
  {
    "bids_usd": 33491.017,
    "bids_quantity": 590730,
    "asks_usd": 52242.863,
    "asks_quantity": 899960,
    "time": 1754956800000,
    "pair_info": {
      "instrument_id": "TANSSIUSDT",
      "base_asset": "TANSSI",
      "quote_asset": "USDT",
      "exchange": "Bybit"
    },
    "fetched_at": "2025-09-05T11:34:49.756Z"
  },
  {
    "bids_usd": 41190.6965,
    "bids_quantity": 726060,
    "asks_usd": 43189.536,
    "asks_quantity": 747510,
    "time": 1755043200000,
    "pair_info": {
      "instrument_id": "TANSSIUSDT",
      "base_asset": "TANSSI",
      "quote_asset": "USDT",
      "exchange": "Bybit"
    },
    "fetched_at": "2025-09-05T11:34:49.756Z"
  },
  {
    "bids_usd": 50040.5141,
    "bids_quantity": 862360,
    "asks_usd": 37930.0841,
    "asks_quantity": 641120,
    "time": 1755129600000,
    "pair_info": {
      "instrument_id": "TANSSIUSDT",
      "base_asset": "TANSSI",
      "quote_asset": "USDT",
      "exchange": "Bybit"
    },
    "fetched_at": "2025-09-05T11:34:49.756Z"
  },
  {
    "bids_usd": 35314.8528,
    "bids_quantity": 706110,
    "asks_usd": 35976.5487,
    "asks_quantity": 707550,
    "time": 1755216000000,
    "pair_info": {
      "instrument_id": "TANSSIUSDT",
      "base_asset": "TANSSI",
      "quote_asset": "USDT",
      "exchange": "Bybit"
    },
    "fetched_at": "2025-09-05T11:34:49.756Z"
  },
  {
    "bids_usd": 49986.5147,
    "bids_quantity": 1078240,
    "asks_usd": 43982.5797,
    "asks_quantity": 931330,
    "time": 1755302400000,
    "pair_info": {
      "instrument_id": "TANSSIUSDT",
      "base_asset": "TANSSI",
      "quote_asset": "USDT",
      "exchange": "Bybit"
    },
    "fetched_at": "2025-09-05T11:34:49.756Z"
  },
  {
    "bids_usd": 26405.7067,
    "bids_quantity": 531630,
    "asks_usd": 31347.5909,
    "asks_quantity": 620480,
    "time": 1755388800000,
    "pair_info": {
      "instrument_id": "TANSSIUSDT",
      "base_asset": "TANSSI",
      "quote_asset": "USDT",
      "exchange": "Bybit"
    },
    "fetched_at": "2025-09-05T11:34:49.756Z"
  },
  {
    "bids_usd": 22364.5751,
    "bids_quantity": 459790,
    "asks_usd": 28517.3658,
    "asks_quantity": 575760,
    "time": 1755475200000,
    "pair_info": {
      "instrument_id": "TANSSIUSDT",
      "base_asset": "TANSSI",
      "quote_asset": "USDT",
      "exchange": "Bybit"
    },
    "fetched_at": "2025-09-05T11:34:49.756Z"
  },
  {
    "bids_usd": 31885.6893,
    "bids_quantity": 650180,
    "asks_usd": 31666.2267,
    "asks_quantity": 634890,
    "time": 1755561600000,
    "pair_info": {
      "instrument_id": "TANSSIUSDT",
      "base_asset": "TANSSI",
      "quote_asset": "USDT",
      "exchange": "Bybit"
    },
    "fetched_at": "2025-09-05T11:34:49.756Z"
  },
  {
    "bids_usd": 22676.0686,
    "bids_quantity": 531740,
    "asks_usd": 22745.0792,
    "asks_quantity": 522540,
    "time": 1755648000000,
    "pair_info": {
      "instrument_id": "TANSSIUSDT",
      "base_asset": "TANSSI",
      "quote_asset": "USDT",
      "exchange": "Bybit"
    },
    "fetched_at": "2025-09-05T11:34:49.756Z"
  },
  {
    "bids_usd": 39411.0416,
    "bids_quantity": 863120,
    "asks_usd": 34140.8428,
    "asks_quantity": 734060,
    "time": 1755734400000,
    "pair_info": {
      "instrument_id": "TANSSIUSDT",
      "base_asset": "TANSSI",
      "quote_asset": "USDT",
      "exchange": "Bybit"
    },
    "fetched_at": "2025-09-05T11:34:49.756Z"
  },
  {
    "bids_usd": 45401.6673,
    "bids_quantity": 1007540,
    "asks_usd": 26976.4921,
    "asks_quantity": 588210,
    "time": 1755820800000,
    "pair_info": {
      "instrument_id": "TANSSIUSDT",
      "base_asset": "TANSSI",
      "quote_asset": "USDT",
      "exchange": "Bybit"
    },
    "fetched_at": "2025-09-05T11:34:49.756Z"
  },
  {
    "bids_usd": 26313.0763,
    "bids_quantity": 550640,
    "asks_usd": 16828.1939,
    "asks_quantity": 345830,
    "time": 1755907200000,
    "pair_info": {
      "instrument_id": "TANSSIUSDT",
      "base_asset": "TANSSI",
      "quote_asset": "USDT",
      "exchange": "Bybit"
    },
    "fetched_at": "2025-09-05T11:34:49.756Z"
  },
  {
    "bids_usd": 30665.1745,
    "bids_quantity": 691630,
    "asks_usd": 30988.5977,
    "asks_quantity": 686370,
    "time": 1755993600000,
    "pair_info": {
      "instrument_id": "TANSSIUSDT",
      "base_asset": "TANSSI",
      "quote_asset": "USDT",
      "exchange": "Bybit"
    },
    "fetched_at": "2025-09-05T11:34:49.756Z"
  },
  {
    "bids_usd": 33239.8744,
    "bids_quantity": 746840,
    "asks_usd": 27563.3846,
    "asks_quantity": 608640,
    "time": 1756080000000,
    "pair_info": {
      "instrument_id": "TANSSIUSDT",
      "base_asset": "TANSSI",
      "quote_asset": "USDT",
      "exchange": "Bybit"
    },
    "fetched_at": "2025-09-05T11:34:49.756Z"
  },
  {
    "bids_usd": 37372.7753,
    "bids_quantity": 948290,
    "asks_usd": 39685.6634,
    "asks_quantity": 987720,
    "time": 1756166400000,
    "pair_info": {
      "instrument_id": "TANSSIUSDT",
      "base_asset": "TANSSI",
      "quote_asset": "USDT",
      "exchange": "Bybit"
    },
    "fetched_at": "2025-09-05T11:34:49.756Z"
  },
  {
    "bids_usd": 32363.3796,
    "bids_quantity": 806510,
    "asks_usd": 20789.959,
    "asks_quantity": 509880,
    "time": 1756252800000,
    "pair_info": {
      "instrument_id": "TANSSIUSDT",
      "base_asset": "TANSSI",
      "quote_asset": "USDT",
      "exchange": "Bybit"
    },
    "fetched_at": "2025-09-05T11:34:49.756Z"
  },
  {
    "bids_usd": 31127.6976,
    "bids_quantity": 788230,
    "asks_usd": 26124.1416,
    "asks_quantity": 650100,
    "time": 1756339200000,
    "pair_info": {
      "instrument_id": "TANSSIUSDT",
      "base_asset": "TANSSI",
      "quote_asset": "USDT",
      "exchange": "Bybit"
    },
    "fetched_at": "2025-09-05T11:34:49.756Z"
  },
  {
    "bids_usd": 38493.8365,
    "bids_quantity": 864880,
    "asks_usd": 30815.6584,
    "asks_quantity": 679630,
    "time": 1756425600000,
    "pair_info": {
      "instrument_id": "TANSSIUSDT",
      "base_asset": "TANSSI",
      "quote_asset": "USDT",
      "exchange": "Bybit"
    },
    "fetched_at": "2025-09-05T11:34:49.756Z"
  },
  {
    "bids_usd": 36228.2248,
    "bids_quantity": 777500,
    "asks_usd": 32345.2492,
    "asks_quantity": 679970,
    "time": 1756512000000,
    "pair_info": {
      "instrument_id": "TANSSIUSDT",
      "base_asset": "TANSSI",
      "quote_asset": "USDT",
      "exchange": "Bybit"
    },
    "fetched_at": "2025-09-05T11:34:49.756Z"
  },
  {
    "bids_usd": 31763.9392,
    "bids_quantity": 756580,
    "asks_usd": 25959.7874,
    "asks_quantity": 606590,
    "time": 1756598400000,
    "pair_info": {
      "instrument_id": "TANSSIUSDT",
      "base_asset": "TANSSI",
      "quote_asset": "USDT",
      "exchange": "Bybit"
    },
    "fetched_at": "2025-09-05T11:34:49.756Z"
  },
  {
    "bids_usd": 34380.4673,
    "bids_quantity": 824540,
    "asks_usd": 32985.5808,
    "asks_quantity": 775040,
    "time": 1756684800000,
    "pair_info": {
      "instrument_id": "TANSSIUSDT",
      "base_asset": "TANSSI",
      "quote_asset": "USDT",
      "exchange": "Bybit"
    },
    "fetched_at": "2025-09-05T11:34:49.756Z"
  },
  {
    "bids_usd": 21037.0183,
    "bids_quantity": 544760,
    "asks_usd": 16617.3697,
    "asks_quantity": 422030,
    "time": 1756771200000,
    "pair_info": {
      "instrument_id": "TANSSIUSDT",
      "base_asset": "TANSSI",
      "quote_asset": "USDT",
      "exchange": "Bybit"
    },
    "fetched_at": "2025-09-05T11:34:49.756Z"
  },
  {
    "bids_usd": 27708.5712,
    "bids_quantity": 695000,
    "asks_usd": 19591.1915,
    "asks_quantity": 480850,
    "time": 1756857600000,
    "pair_info": {
      "instrument_id": "TANSSIUSDT",
      "base_asset": "TANSSI",
      "quote_asset": "USDT",
      "exchange": "Bybit"
    },
    "fetched_at": "2025-09-05T11:34:49.756Z"
  },
  {
    "bids_usd": 16507.8103,
    "bids_quantity": 413450,
    "asks_usd": 19272.1282,
    "asks_quantity": 473270,
    "time": 1756944000000,
    "pair_info": {
      "instrument_id": "TANSSIUSDT",
      "base_asset": "TANSSI",
      "quote_asset": "USDT",
      "exchange": "Bybit"
    },
    "fetched_at": "2025-09-05T11:34:49.756Z"
  },
  {
    "bids_usd": 20059.6779,
    "bids_quantity": 522670,
    "asks_usd": 18249.6091,
    "asks_quantity": 467640,
    "time": 1757030400000,
    "pair_info": {
      "instrument_id": "TANSSIUSDT",
      "base_asset": "TANSSI",
      "quote_asset": "USDT",
      "exchange": "Bybit"
    },
    "fetched_at": "2025-09-05T11:34:49.756Z"
  }
]