{
  "code": "0",
  "data": [
    {
      "instrument_id": "REQUSDT",
      "exchange_name": "Bybit",
      "symbol": "REQ/USDT",
      "current_price": 0.12165,
      "index_price": 0.122,
      "price_change_percent_24h": -5.22,
      "volume_usd": 540099.731,
      "volume_usd_change_percent_24h": 22.98,
      "long_volume_usd": 295393.7032,
      "short_volume_usd": 244706.0278,
      "long_volume_quantity": 13747,
      "short_volume_quantity": 14673,
      "open_interest_quantity": 4382074,
      "open_interest_usd": 533079.3,
      "open_interest_change_percent_24h": 3.08,
      "long_liquidation_usd_24h": 0,
      "short_liquidation_usd_24h": 457.03,
      "funding_rate": 0.01,
      "next_funding_time": 1756915200000,
      "open_interest_volume_radio": 0.987,
      "oi_vol_ratio_change_percent_24h": -16.19
    },
    {
      "instrument_id": "REQ_USDT",
      "exchange_name": "MEXC",
      "symbol": "REQ/USDT",
      "current_price": 0.1216,
      "index_price": 0.122,
      "price_change_percent_24h": -5.36,
      "volume_usd": 358793.271,
      "volume_usd_change_percent_24h": -20.71,
      "long_volume_usd": 174413.177,
      "short_volume_usd": 184380.104,
      "long_volume_quantity": 4252,
      "short_volume_quantity": 4390,
      "open_interest_quantity": 2667500,
      "open_interest_usd": 324634.75,
      "open_interest_change_percent_24h": 133.44,
      "funding_rate": 0.01,
      "open_interest_volume_radio": 0.9048,
      "oi_vol_ratio_change_percent_24h": 194.44
    },
    {
      "instrument_id": "REQ_USDT",
      "exchange_name": "Gate",
      "symbol": "REQ/USDT",
      "current_price": 0.12176,
      "index_price": 0.12211,
      "price_change_percent_24h": -5.47,
      "volume_usd": 16394.1846,
      "volume_usd_change_percent_24h": -51.83,
      "long_volume_usd": 6719.9508,
      "short_volume_usd": 9674.2338,
      "long_volume_quantity": 96,
      "short_volume_quantity": 129,
      "open_interest_quantity": 374088,
      "open_interest_usd": 45548.95488,
      "open_interest_change_percent_24h": -2.36,
      "funding_rate": 0.01,
      "open_interest_volume_radio": 2.7784,
      "oi_vol_ratio_change_percent_24h": 102.73
    }
  ]
}