{
  "code": "0",
  "data": [
    {
      "instrument_id": "CETUSUSDT",
      "exchange_name": "Binance",
      "symbol": "CETUS/USDT",
      "current_price": 0.08801,
      "index_price": 0.08817806,
      "price_change_percent_24h": -1.62,
      "volume_usd": 4075228.25016,
      "volume_usd_change_percent_24h": -9.66,
      "long_volume_usd": 1853254.9857,
      "short_volume_usd": 2221973.26446,
      "long_volume_quantity": 48791,
      "short_volume_quantity": 74168,
      "open_interest_quantity": 42351699,
      "open_interest_usd": 3728220.06297,
      "open_interest_change_percent_24h": -3.8,
      "long_liquidation_usd_24h": 0,
      "short_liquidation_usd_24h": 8067.25,
      "funding_rate": 0.005,
      "next_funding_time": 1757001600000,
      "open_interest_volume_radio": 0.9148,
      "oi_vol_ratio_change_percent_24h": 6.48
    },
    {
      "instrument_id": "CETUSUSDT_UMCBL",
      "exchange_name": "Bitget",
      "symbol": "CETUS/USDT",
      "current_price": 0.08813,
      "index_price": 0.0882321217112458,
      "price_change_percent_24h": -1.61,
      "volume_usd": 549237.53588,
      "volume_usd_change_percent_24h": -69.58,
      "long_volume_usd": 269248.0223,
      "short_volume_usd": 279989.51378,
      "long_volume_quantity": 3739,
      "short_volume_quantity": 4025,
      "open_interest_quantity": 36897885,
      "open_interest_usd": 3258083.2455,
      "open_interest_change_percent_24h": -6.46,
      "funding_rate": 0.005,
      "next_funding_time": 1757001600000,
      "open_interest_volume_radio": 5.932,
      "oi_vol_ratio_change_percent_24h": 207.5
    },
    {
      "instrument_id": "CETUSUSDT",
      "exchange_name": "Bybit",
      "symbol": "CETUS/USDT",
      "current_price": 0.08814,
      "index_price": 0.08821,
      "price_change_percent_24h": -1.51,
      "volume_usd": 526556.15408,
      "volume_usd_change_percent_24h": 11.45,
      "long_volume_usd": 238419.1746,
      "short_volume_usd": 288136.99958,
      "long_volume_quantity": 3785,
      "short_volume_quantity": 4380,
      "open_interest_quantity": 24037910,
      "open_interest_usd": 2120384.04,
      "open_interest_change_percent_24h": -1.38,
      "long_liquidation_usd_24h": 57.82,
      "short_liquidation_usd_24h": 0,
      "funding_rate": 0.005,
      "next_funding_time": 1757001600000,
      "open_interest_volume_radio": 4.0269,
      "oi_vol_ratio_change_percent_24h": -11.51
    },
    {
      "instrument_id": "CETUS_USDT",
      "exchange_name": "MEXC",
      "symbol": "CETUS/USDT",
      "current_price": 0.0881,
      "index_price": 0.0882,
      "price_change_percent_24h": -1.51,
      "volume_usd": 1166039.0082,
      "volume_usd_change_percent_24h": 50.52,
      "long_volume_usd": 594802.9637,
      "short_volume_usd": 571236.0345,
      "long_volume_quantity": 2655,
      "short_volume_quantity": 2660,
      "open_interest_quantity": 21121930,
      "open_interest_usd": 1862109.3488,
      "open_interest_change_percent_24h": 17.08,
      "funding_rate": 0.005,
      "open_interest_volume_radio": 1.597,
      "oi_vol_ratio_change_percent_24h": -22.21
    },
    {
      "instrument_id": "CETUS-USDT-SWAP",
      "exchange_name": "OKX",
      "symbol": "CETUS/USDT",
      "current_price": 0.088,
      "index_price": 0.08819,
      "price_change_percent_24h": -1.62,
      "volume_usd": 2027294.5524,
      "volume_usd_change_percent_24h": 4.02,
      "long_volume_usd": 945662.0519,
      "short_volume_usd": 1081632.5005,
      "long_volume_quantity": 13842,
      "short_volume_quantity": 12856,
      "open_interest_quantity": 18181730,
      "open_interest_usd": 1599992.24,
      "open_interest_change_percent_24h": -2.32,
      "long_liquidation_usd_24h": 0,
      "short_liquidation_usd_24h": 55.78,
      "funding_rate": 0.005,
      "next_funding_time": 1757001600000,
      "open_interest_volume_radio": 0.7892,
      "oi_vol_ratio_change_percent_24h": -6.09
    },
    {
      "instrument_id": "CETUS_PERP",
      "exchange_name": "WhiteBIT",
      "symbol": "CETUS/USDT",
      "current_price": 0.08805,
      "index_price": 0.0881,
      "price_change_percent_24h": -1.59,
      "volume_usd": 2567498.4564,
      "volume_usd_change_percent_24h": -39.94,
      "long_volume_usd": 1333330.8582,
      "short_volume_usd": 1234167.5982,
      "long_volume_quantity": 31706,
      "short_volume_quantity": 26245,
      "open_interest_quantity": 11280080,
      "open_interest_usd": 993211.044,
      "open_interest_change_percent_24h": -3.23,
      "funding_rate": 0.01567,
      "next_funding_time": 1757001600000,
      "open_interest_volume_radio": 0.3868,
      "oi_vol_ratio_change_percent_24h": 61.1
    },
    {
      "instrument_id": "CETUSUSDTM",
      "exchange_name": "KuCoin",
      "symbol": "CETUS/USDT",
      "current_price": 0.08809,
      "index_price": 0.08817,
      "price_change_percent_24h": -1.52,
      "volume_usd": 565211.2186,
      "volume_usd_change_percent_24h": -38.36,
      "long_volume_usd": 268218.2214,
      "short_volume_usd": 296992.9972,
      "long_volume_quantity": 2183,
      "short_volume_quantity": 2541,
      "open_interest_quantity": 8913000,
      "open_interest_usd": 786393.99,
      "open_interest_change_percent_24h": -2.88,
      "funding_rate": -0.0074,
      "next_funding_time": 1757001576880,
      "open_interest_volume_radio": 1.3913,
      "oi_vol_ratio_change_percent_24h": 57.57
    },
    {
      "instrument_id": "CETUS_USDT",
      "exchange_name": "Gate",
      "symbol": "CETUS/USDT",
      "current_price": 0.08803,
      "index_price": 0.088206,
      "price_change_percent_24h": -1.52,
      "volume_usd": 1121150.3851,
      "volume_usd_change_percent_24h": 19.59,
      "long_volume_usd": 562145.7888,
      "short_volume_usd": 559004.5963,
      "long_volume_quantity": 4383,
      "short_volume_quantity": 4235,
      "open_interest_quantity": 5892180,
      "open_interest_usd": 518688.6054,
      "open_interest_change_percent_24h": -4.8,
      "funding_rate": -0.0379,
      "open_interest_volume_radio": 0.4626,
      "oi_vol_ratio_change_percent_24h": -20.41
    },
    {
      "instrument_id": "CETUS-USDT",
      "exchange_name": "BingX",
      "symbol": "CETUS/USDT",
      "current_price": 0.0881,
      "index_price": 0.08821,
      "price_change_percent_24h": -1.55,
      "volume_usd": 718973.5284,
      "volume_usd_change_percent_24h": -38.15,
      "long_volume_usd": 349838.58,
      "short_volume_usd": 369134.9184,
      "long_volume_quantity": 32244,
      "short_volume_quantity": 33010,
      "open_interest_quantity": 4839438.5567,
      "open_interest_usd": 426499.72,
      "open_interest_change_percent_24h": -19.17,
      "funding_rate": 0.005,
      "next_funding_time": 1757001600000,
      "open_interest_volume_radio": 0.5932,
      "oi_vol_ratio_change_percent_24h": 30.69
    },
    {
      "instrument_id": "CETUSUSDT",
      "exchange_name": "Bitunix",
      "symbol": "CETUS/USDT",
      "current_price": 0.08804,
      "index_price": 0.08821,
      "price_change_percent_24h": -1.6,
      "volume_usd": 461084.57232,
      "volume_usd_change_percent_24h": -10.56,
      "long_volume_usd": 218927.26933,
      "short_volume_usd": 242157.30319,
      "long_volume_quantity": 11747,
      "short_volume_quantity": 17534,
      "open_interest_quantity": 2022621,
      "open_interest_usd": 178314.26736,
      "open_interest_change_percent_24h": -1.35,
      "funding_rate": 0.005,
      "next_funding_time": 1757001600000,
      "open_interest_volume_radio": 0.3867,
      "oi_vol_ratio_change_percent_24h": 10.3
    },
    {
      "instrument_id": "CETUSUSDT",
      "exchange_name": "CoinEx",
      "symbol": "CETUS/USDT",
      "current_price": 0.088205,
      "index_price": 0.088232,
      "price_change_percent_24h": -1.63,
      "volume_usd": 95260.856688,
      "volume_usd_change_percent_24h": 60.86,
      "long_volume_usd": 52029.310565,
      "short_volume_usd": 43231.556223,
      "long_volume_quantity": 1630,
      "short_volume_quantity": 1634,
      "open_interest_quantity": 1906895,
      "open_interest_usd": 168197.673475,
      "open_interest_change_percent_24h": 10.05,
      "funding_rate": 0.016717,
      "next_funding_time": 1757001545208,
      "open_interest_volume_radio": 1.7657,
      "oi_vol_ratio_change_percent_24h": -31.58
    },
    {
      "instrument_id": "PF_CETUSUSD",
      "exchange_name": "Kraken",
      "symbol": "CETUS/USDT",
      "current_price": 0.08838,
      "index_price": 0.088206,
      "price_change_percent_24h": -0.43,
      "volume_usd": 853.06,
      "volume_usd_change_percent_24h": 5095.06,
      "long_volume_usd": 853.06,
      "short_volume_usd": 0,
      "long_volume_quantity": 10,
      "short_volume_quantity": 0,
      "open_interest_quantity": 152428,
      "open_interest_usd": 13471.58664,
      "open_interest_change_percent_24h": -6.34,
      "funding_rate": -0.0047204711111111,
      "next_funding_time": 1756990800000,
      "open_interest_volume_radio": 15.7921,
      "oi_vol_ratio_change_percent_24h": -98.2
    },
    {
      "instrument_id": "CETUS-USD",
      "exchange_name": "dYdX",
      "symbol": "CETUS/USD",
      "current_price": 0.0892,
      "price_change_percent_24h": 0,
      "volume_usd": 249.76,
      "volume_usd_change_percent_24h": 0,
      "long_volume_usd": 249.76,
      "short_volume_usd": 0,
      "long_volume_quantity": 1,
      "short_volume_quantity": 0,
      "open_interest_quantity": 3000,
      "open_interest_usd": 268.33416708,
      "open_interest_change_percent_24h": 0.39,
      "funding_rate": 0.00125,
      "open_interest_volume_radio": 1.0744,
      "oi_vol_ratio_change_percent_24h": 0.39
    }
  ]
}